openapi_builder/__init__.py
openapi_builder/__meta__.py
openapi_builder/builder.py
openapi_builder/constants.py
openapi_builder/decorators.py
openapi_builder/documentation.py
openapi_builder/exceptions.py
openapi_builder/specification.py
openapi_builder/util.py
openapi_builder/blueprint/__init__.py
openapi_builder/blueprint/blueprint.py
openapi_builder/blueprint/get.py
openapi_builder/blueprint/specification.py
openapi_builder/converters/__init__.py
openapi_builder/converters/defaults/__init__.py
openapi_builder/converters/defaults/base.py
openapi_builder/converters/defaults/default_converters.py
openapi_builder/converters/defaults/manager.py
openapi_builder/converters/parameter/__init__.py
openapi_builder/converters/parameter/base.py
openapi_builder/converters/parameter/flask_converters.py
openapi_builder/converters/parameter/manager.py
openapi_builder/converters/schema/__init__.py
openapi_builder/converters/schema/base.py
openapi_builder/converters/schema/halogen.py
openapi_builder/converters/schema/manager.py
openapi_builder/converters/schema/marshmallow.py
openapi_builder/parsers/__init__.py
openapi_builder/parsers/docstring.py
openapi_builder/templates/docs.html
openapi_builder-0.3.0.dist-info/LICENSE
openapi_builder-0.3.0.dist-info/METADATA
openapi_builder-0.3.0.dist-info/WHEEL
openapi_builder-0.3.0.dist-info/top_level.txt
openapi_builder-0.3.0.dist-info/RECORD
