Metadata-Version: 2.1
Name: openapi-builder
Version: 0.3.0
Summary: A Flask extension to automatically add OpenAPI documentation for your Flask app.
Home-page: https://github.com/FlyingBird95/openapi-builder
Author: Patrick Vogel
Author-email: patrickvogel@live.nl
License: MIT
Classifier: Natural Language :: English
Classifier: Programming Language :: Python
Classifier: Programming Language :: Python :: 3
Classifier: Programming Language :: Python :: 3.6
Classifier: Programming Language :: Python :: 3.7
Classifier: Programming Language :: Python :: 3.8
Classifier: Programming Language :: Python :: 3.9
Classifier: Programming Language :: Python :: 3.10
Requires-Python: >=3.6
License-File: LICENSE
Requires-Dist: flask (==2.0.3)
Provides-Extra: all
Requires-Dist: black (==22.3.0) ; extra == 'all'
Requires-Dist: halogen (==1.7.0) ; extra == 'all'
Requires-Dist: marshmallow (==3.14.1) ; extra == 'all'
Requires-Dist: pre-commit (==2.18.1) ; extra == 'all'
Requires-Dist: pytest-cov (==3.0.0) ; extra == 'all'
Requires-Dist: pytest-factoryboy (==2.1.0) ; extra == 'all'
Requires-Dist: pytest-flake8 (==1.1.1) ; extra == 'all'
Requires-Dist: pytest (==7.0.1) ; extra == 'all'
Requires-Dist: readthedocs-sphinx-search (==0.1.1) ; extra == 'all'
Requires-Dist: sphinx-autobuild (==2021.3.14) ; extra == 'all'
Requires-Dist: sphinx-book-theme (==0.2.0) ; extra == 'all'
Requires-Dist: sphinx (==4.5.0) ; extra == 'all'
Provides-Extra: dev
Requires-Dist: black (==22.3.0) ; extra == 'dev'
Requires-Dist: marshmallow (==3.14.1) ; extra == 'dev'
Requires-Dist: pre-commit (==2.18.1) ; extra == 'dev'
Provides-Extra: docs
Requires-Dist: marshmallow (==3.14.1) ; extra == 'docs'
Requires-Dist: readthedocs-sphinx-search (==0.1.1) ; extra == 'docs'
Requires-Dist: sphinx (==4.5.0) ; extra == 'docs'
Requires-Dist: sphinx-autobuild (==2021.3.14) ; extra == 'docs'
Requires-Dist: sphinx-book-theme (==0.2.0) ; extra == 'docs'
Provides-Extra: test
Requires-Dist: halogen (==1.7.0) ; extra == 'test'
Requires-Dist: marshmallow (==3.14.1) ; extra == 'test'
Requires-Dist: pytest (==7.0.1) ; extra == 'test'
Requires-Dist: pytest-cov (==3.0.0) ; extra == 'test'
Requires-Dist: pytest-factoryboy (==2.1.0) ; extra == 'test'
Requires-Dist: pytest-flake8 (==1.1.1) ; extra == 'test'
